odoo10_addon_account_payment_unece-10.0.1.0.1-py2.7-nspkg.pth
odoo/addons/account_payment_unece/README.rst
odoo/addons/account_payment_unece/__init__.py
odoo/addons/account_payment_unece/__manifest__.py
odoo/addons/account_payment_unece/data/account_payment_method.xml
odoo/addons/account_payment_unece/data/unece.xml
odoo/addons/account_payment_unece/models/__init__.py
odoo/addons/account_payment_unece/models/account_payment_method.py
odoo/addons/account_payment_unece/models/unece_code_list.py
odoo/addons/account_payment_unece/tests/__init__.py
odoo/addons/account_payment_unece/tests/test_account_invoice.py
odoo/addons/account_payment_unece/views/account_payment_method.xml
odoo10_addon_account_payment_unece-10.0.1.0.1.dist-info/DESCRIPTION.rst
odoo10_addon_account_payment_unece-10.0.1.0.1.dist-info/METADATA
odoo10_addon_account_payment_unece-10.0.1.0.1.dist-info/RECORD
odoo10_addon_account_payment_unece-10.0.1.0.1.dist-info/WHEEL
odoo10_addon_account_payment_unece-10.0.1.0.1.dist-info/metadata.json
odoo10_addon_account_payment_unece-10.0.1.0.1.dist-info/namespace_packages.txt
odoo10_addon_account_payment_unece-10.0.1.0.1.dist-info/top_level.txt
